nizaba/__init__.py
nizaba/api/__init__.py
nizaba/api/set_history.py
nizaba/lang/__init__.py
nizaba/lang/core.py
nizaba/providers/__init__.py
nizaba/providers/openai.py
nizaba-0.0.5.dist-info/LICENSE
nizaba-0.0.5.dist-info/METADATA
nizaba-0.0.5.dist-info/WHEEL
nizaba-0.0.5.dist-info/top_level.txt
nizaba-0.0.5.dist-info/RECORD
