Metadata-Version: 2.1
Name: nizaba
Version: 0.0.5
Summary: Python library for Nizaba
Author: Arcadia78 Solutions
Author-email: david@arcadia78.com
Classifier: Programming Language :: Python :: 3
Classifier: License :: OSI Approved :: BSD License
Classifier: Operating System :: OS Independent
Requires-Python: >=3.6
License-File: LICENSE
